fagents/__init__.py
fagents/fagents.py
fagents-1.2.dist-info/LICENSE
fagents-1.2.dist-info/METADATA
fagents-1.2.dist-info/WHEEL
fagents-1.2.dist-info/top_level.txt
fagents-1.2.dist-info/RECORD
