Metadata-Version: 2.1
Name: fagents
Version: 1.2
Summary: A simple Python package designed to generate fake user agents
Home-page: https://github.com/Abodx9/Fagents
Author: Abodx
Author-email: abodx@gmx.de
Project-URL: Bug Tracker, https://github.com/Abodx9/Fagents/issues
Classifier: Programming Language :: Python :: 3
Classifier: License :: OSI Approved :: MIT License
Classifier: Operating System :: OS Independent
Requires-Python: >=3.6
License-File: LICENSE
